snmpy/__init__.py
snmpy/snmpy.py
snmpy-1.0.0.dist-info/top_level.txt
snmpy-1.0.0.dist-info/METADATA
snmpy-1.0.0.dist-info/DESCRIPTION.rst
snmpy-1.0.0.dist-info/metadata.json
snmpy-1.0.0.dist-info/WHEEL
snmpy-1.0.0.dist-info/RECORD
