Metadata-Version: 2.0
Name: snmpy
Version: 1.0.0
Summary: Simple pysnmp wrapper.
Home-page: https://github.com/SimplicityGuy/snmpy
Author: Robert Wlodarczyk
Author-email: robert@simplicityguy.com
License: Apache License 2.0
Keywords: snmp monitoring
Platform: UNKNOWN
Classifier: Development Status :: 5 - Production/Stable
Classifier: Environment :: Console
Classifier: Intended Audience :: Developers
Classifier: Intended Audience :: System Administrators
Classifier: License :: OSI Approved :: Apache Software License
Classifier: Programming Language :: Python :: 2.7
Classifier: Programming Language :: Python :: 3.3
Classifier: Programming Language :: Python :: 3.4
Classifier: Programming Language :: Python :: 3.5
Classifier: Programming Language :: Python :: 3.6
Classifier: Topic :: System :: Monitoring
Requires-Dist: pysnmp
